fasio/__init__.py
fasio/asyncsocket.py
fasio/eventloop.py
fasio/file.py
fasio/promise.py
fasio/queue.py
fasio/reactors.py
fasio/thread.py
fasio-0.2.4.dist-info/licenses/LICENSE
fasio-0.2.4.dist-info/METADATA
fasio-0.2.4.dist-info/WHEEL
fasio-0.2.4.dist-info/top_level.txt
fasio-0.2.4.dist-info/RECORD
