Metadata-Version: 2.4
Name: fasio
Version: 0.2.4
Summary: A fast asynchronous coroutine executor for asynchronous programming and fast I/O.
Home-page: https://github.com/iadityanath8/Fasio
Author: Nemesis
Author-email: iadityanath8@gmail.com
Classifier: Programming Language :: Python :: 3
Classifier: License :: OSI Approved :: GNU General Public License v2 (GPLv2)
Classifier: Operating System :: OS Independent
Requires-Python: >=3.6
License-File: LICENSE
Dynamic: author
Dynamic: author-email
Dynamic: classifier
Dynamic: description
Dynamic: description-content-type
Dynamic: home-page
Dynamic: license-file
Dynamic: requires-python
Dynamic: summary
